{
    "facilities": {
        "dls": {
            "keyName": "dls",
            "title": "DIAMOND",
            "icatUrl": "https://facilities02.esc.rl.ac.uk:8181",
            "connectProxyPath": "dls/",
            "idsUrl": "https://fdsstoraged20.fds.rl.ac.uk:8181",
            "facilityId": 1,
            "hierarchy": [
                "facility",
                "instrument",
                "investigation",
                "dataset",
                "datafile"
            ],
            "browseColumns": {
                "instrument": [
                    {
                        "name": "id",
                        "title": "Id",
                        "visible": false
                    },
                    {
                        "name": "name",
                        "title": "Name",
                        "link": true,
                        "sortByDefault" : "asc"
                    },
                    {
                        "name": "fullName",
                        "title": "Full Name",
                        "sortable": false
                    }
                ],
                "investigation": [
                    {
                        "name": null,
                        "title": "",
                        "checkbox": true
                    },
                    {
                        "name": "id",
                        "title": "Id",
                        "style": "firstColumn",
                        "visible": false
                    },
                    {
                        "name": "title",
                        "title": "Title",
                        "style": "secondColumn",
                        "sortable": false,
                        "link": true,
                        "expressionFilter": {
                            "type": "string",
                            "name": "characters",
                            "characters": 80
                        },
                        "sortByDefault" : "asc"
                    },
                    {
                        "name": "visitId",
                        "title": "Visit Id"
                    },
                    {
                        "name": "startDate",
                        "title": "Start Date",
                        "expressionFilter": {
                            "type": "date",
                            "format": "dd-MM-yyyy",
                            "timezone": "UTC"
                        }
                    },
                    {
                        "name": "endDate",
                        "title": "End Date",
                        "expressionFilter": {
                            "type": "date",
                            "format": "dd-MM-yyyy",
                            "timezone": "UTC"
                        }
                    }
                ],
                "dataset": [
                    {
                        "name": null,
                        "title": "",
                        "checkbox": true,
                        "sortByDefault" : "asc"
                    },
                    {
                        "name": "name",
                        "title": "Name",
                        "link": true
                    },
                    {
                        "name": "createTime",
                        "title": "Create Time"
                    },
                    {
                        "name": "modTime",
                        "title": "Modified Time"
                    }
                ],
                "datafile": [
                    {
                        "name": null,
                        "title": "",
                        "checkbox": true
                    },
                    {
                        "name": "name",
                        "title": "Name",
                        "expressionFilter": {
                            "type": "string",
                            "name": "characters",
                            "characters": 80
                        },
                        "sortByDefault" : "asc"
                    },
                    {
                        "name": "fileSize",
                        "title": "File Size",
                        "expressionFilter": {
                            "type": "bytes"
                        }
                    },
                    {
                        "name": "modTime",
                        "title": "Modified Time"
                    }
                ]
            }
        },
        "isis": {
            "keyName": "isis",
            "title": "ISIS Laser",
            "icatUrl": "https://icatdev.isis.cclrc.ac.uk",
            "connectProxyPath": "isis/",
            "idsUrl": "https://facilities.esc.rl.ac.uk:8181",
            "facilityId": 1,
            "hierarchy": [
                "facility",
                "instrument",
                "investigation",
                "dataset",
                "datafile"
            ],
            "browseColumns": {
                "instrument": [
                    {
                        "name": "id",
                        "title": "Id"
                    },
                    {
                        "name": "name",
                        "title": "Name",
                        "link": true
                    },
                    {
                        "name": "fullName",
                        "title": "Full Name"
                    }
                ],
                "investigation": [
                    {
                        "name": "id",
                        "title": "Id",
                        "style": "firstColumn",
                        "visible": false
                    },
                    {
                        "name": "title",
                        "title": "Title",
                        "style": "secondColumn",
                        "sortable": false,
                        "link": true,
                        "expressionFilter": {
                            "type": "string",
                            "name": "characters",
                            "characters": 80
                        }
                    },
                    {
                        "name": "visitId",
                        "title": "Visit Id"
                    },
                    {
                        "name": "startDate",
                        "title": "Start Date",
                        "expressionFilter": {
                            "type": "date",
                            "format": "dd-MM-yyyy",
                            "timezone": "UTC"
                        }
                    },
                    {
                        "name": "endDate",
                        "title": "End Date",
                        "expressionFilter": {
                            "type": "date",
                            "format": "dd-MM-yyyy",
                            "timezone": "UTC"
                        }
                    }
                ],
                "dataset": [
                    {
                        "name": null,
                        "title": "",
                        "checkbox": true
                    },
                    {
                        "name": "name",
                        "title": "Name",
                        "link": true
                    },
                    {
                        "name": "createTime",
                        "title": "Create Time"
                    },
                    {
                        "name": "modTime",
                        "title": "Modified Time"
                    }
                ],
                "datafile": [
                    {
                        "name": "name",
                        "title": "Name",
                        "expressionFilter": {
                            "type": "string",
                            "name": "characters",
                            "characters": 80
                        }
                    },
                    {
                        "name": "fileSize",
                        "title": "File Size",
                        "expressionFilter": {
                            "type": "bytes"
                        }
                    },
                    {
                        "name": "modTime",
                        "title": "Modified Time"
                    }
                ]
            }
        }
    },
    "site": {
        "pagingType": "page",
        "useFileForData": false,
        "useFileForSession": true,
        "browseMaxRows": 6,
        "facilitiesColumns": [
            {
                "name": "name",
                "title": "Name",
                "link": true,
                "sortByDefault": "asc"
            },
            {
                "name": "fullName",
                "title": "Full Name"
            }
        ]
    }
}